LICENSE
MANIFEST.in
README.md
VERSION
pyproject.toml
requirements.txt
setup.py
MangaReaderScraper.egg-info/PKG-INFO
MangaReaderScraper.egg-info/SOURCES.txt
MangaReaderScraper.egg-info/dependency_links.txt
MangaReaderScraper.egg-info/entry_points.txt
MangaReaderScraper.egg-info/requires.txt
MangaReaderScraper.egg-info/top_level.txt
scraper/__init__.py
scraper/__main__.py
scraper/download.py
scraper/exceptions.py
scraper/manga.py
scraper/menu.py
scraper/new_types.py
scraper/utils.py
scraper/parsers/__init__.py
scraper/parsers/base.py
scraper/parsers/mangafast.py
scraper/parsers/mangakaka.py
scraper/parsers/mangareader.py
scraper/parsers/types.py
scraper/uploaders/__init__.py
scraper/uploaders/base.py
scraper/uploaders/types.py
scraper/uploaders/uploaders.py