Metadata-Version: 2.1
Name: MangaReaderScraper
Version: 0.51
Summary: Manga scraper
Home-page: https://github.com/superDross/MangaReaderScraper
Author: superDross
Author-email: dross78375@gmail.com
License: UNKNOWN
Platform: UNKNOWN
Classifier: Programming Language :: Python :: 3
Classifier: Operating System :: POSIX :: Linux
Classifier: License :: OSI Approved :: GNU General Public License v3 (GPLv3)
Requires-Python: >=3.7
